ke2daira/__init__.py
ke2daira/kana2mora.py
ke2daira/main.py
ke2daira-0.2.0.dist-info/LICENSE
ke2daira-0.2.0.dist-info/WHEEL
ke2daira-0.2.0.dist-info/METADATA
ke2daira-0.2.0.dist-info/RECORD
