Metadata-Version: 2.1
Name: ke2daira
Version: 0.2.0
Summary: A Python implementaion of ke2daira
Home-page: https://github.com/otariidae/ke2daira.py
License: Apache-2.0
Author: otariidae
Author-email: otariidae@users.noreply.github.com
Requires-Python: >=3.8,<4.0
Classifier: License :: OSI Approved :: Apache Software License
Classifier: Programming Language :: Python :: 3
Classifier: Programming Language :: Python :: 3.8
Classifier: Programming Language :: Python :: 3.9
Requires-Dist: Janome (>=0.4.1,<0.5.0)
Project-URL: Repository, https://github.com/otariidae/ke2daira.js
